Workbook
Name NativeTimeline_Date: #N/A
Name Slicer_Bank1: #N/A
Name Slicer_Date: #N/A
Name Slicer_Platform: #N/A

Sheet Dashboard
A2: ="Social Media Dashboard "&'Headline Pivots'!$E$1 -> Social Media Dashboard Jan to Dec
B19: Number of Followers by Bank
B20: Bank | C20: Total Number of Followers | D20: Trend | E20: Facebook | F20: Instagram | G20: Linkedin | H20: Twitter
B21: =SparklinePivot!A5 -> Chase | C21: =IFERROR(GETPIVOTDATA("Followers",SparklinePivot!$A$3,"Bank",SparklinePivot!A5),"") -> 106290171 | D21: =REPT("|",Dashboard!C21/MAX(Dashboard!$C$21:$C$29)*100) -> ||||||||||||||||||||||||||||||||||||||||||||||||||||||||||||||||||||||||||||||||||||||||||||||||||||
B22: =SparklinePivot!A6 -> Bank of America | C22: =IFERROR(GETPIVOTDATA("Followers",SparklinePivot!$A$3,"Bank",SparklinePivot!A6),"") -> 99986214 | D22: =REPT("|",Dashboard!C22/MAX(Dashboard!$C$21:$C$29)*100) -> ||||||||||||||||||||||||||||||||||||||||||||||||||||||||||||||||||||||||||||||||||||||||||||||
B23: =SparklinePivot!A7 -> Citi | C23: =IFERROR(GETPIVOTDATA("Followers",SparklinePivot!$A$3,"Bank",SparklinePivot!A7),"") -> 95102109 | D23: =REPT("|",Dashboard!C23/MAX(Dashboard!$C$21:$C$29)*100) -> |||||||||||||||||||||||||||||||||||||||||||||||||||||||||||||||||||||||||||||||||||||||||
B24: =SparklinePivot!A8 -> Capital One | C24: =IFERROR(GETPIVOTDATA("Followers",SparklinePivot!$A$3,"Bank",SparklinePivot!A8),"") -> 64886458 | D24: =REPT("|",Dashboard!C24/MAX(Dashboard!$C$21:$C$29)*100) -> |||||||||||||||||||||||||||||||||||||||||||||||||||||||||||||
B25: =SparklinePivot!A9 -> US Bank | C25: =IFERROR(GETPIVOTDATA("Followers",SparklinePivot!$A$3,"Bank",SparklinePivot!A9),"") -> 11760816 | D25: =REPT("|",Dashboard!C25/MAX(Dashboard!$C$21:$C$29)*100) -> |||||||||||
B26: =SparklinePivot!A10 -> PNC | C26: =IFERROR(GETPIVOTDATA("Followers",SparklinePivot!$A$3,"Bank",SparklinePivot!A10),"") -> 9091220 | D26: =REPT("|",Dashboard!C26/MAX(Dashboard!$C$21:$C$29)*100) -> ||||||||
B27: =SparklinePivot!A11 -> Truist | C27: =IFERROR(GETPIVOTDATA("Followers",SparklinePivot!$A$3,"Bank",SparklinePivot!A11),"") -> 5025675 | D27: =REPT("|",Dashboard!C27/MAX(Dashboard!$C$21:$C$29)*100) -> ||||
B28: =SparklinePivot!A12 -> Grand Total | C28: =IFERROR(GETPIVOTDATA("Followers",SparklinePivot!$A$3,"Bank",SparklinePivot!A12),"") | D28: =REPT("|",Dashboard!C28/MAX(Dashboard!$C$21:$C$29)*100) -> #VALUE!
B29: =SparklinePivot!A13 -> 0 | C29: =IFERROR(GETPIVOTDATA("Followers",SparklinePivot!$A$3,"Bank",SparklinePivot!A13),"") | D29: =REPT("|",Dashboard!C29/MAX(Dashboard!$C$21:$C$29)*100) -> #VALUE!

Sheet Audience Counts
A1: Platform | B1: Bank | C1: Account | D1: Date | E1: Followers
A2: Facebook | B2: Bank of America | C2: Bank of America | D2: 44589 | E2: 2779295
A3: Facebook | B3: Capital One | C3: Capital One | D3: 44589 | E3: 3952818
A4: Facebook | B4: Capital One | C4: Capital One Café | D4: 44589 | E4: 96736
A5: Facebook | B5: Capital One | C5: Capital One Careers | D5: 44589 | E5: 14777
A6: Facebook | B6: Capital One | C6: CapitalOne Business | D6: 44589 | E6: 160008
A7: Facebook | B7: Chase | C7: Chase | D7: 44589 | E7: 3702495
A8: Facebook | B8: Chase | C8: JPMorgan Chase & Co. | D8: 44589 | E8: 400833
A9: Facebook | B9: Chase | C9: United MileagePlus Cards by Chase | D9: 44589 | E9: 212458
A10: Facebook | B10: Citi | C10: Citi | D10: 44589 | E10: 1201072
A11: Facebook | B11: Citi | C11: Citibank US | D11: 44589 | E11: 1144626
A12: Facebook | B12: Citi | C12: Citi Careers | D12: 44589 | E12: 215149
A13: Facebook | B13: Wells Fargo | C13: Wells Fargo | D13: 44589 | E13: 1141858
... A33: LinkedIn | B33: Wells Fargo | C33: Wells Fargo Advisors | D33: 44589 | E33: 94341
A34: LinkedIn | B34: Wells Fargo | C34: Wells Fargo Asset Management | D34: 44589 | E34: NA
A35: LinkedIn | B35: PNC | C35: PNC | D35: 44589 | E35: 225034
A36: LinkedIn | B36: PNC | C36: PNC Business Banking | D36: 44589 | E36: 13128
A37: LinkedIn | B37: PNC | C37: PNC Investments | D37: 44589 | E37: NA
A38: LinkedIn | B38: PNC | C38: PNC Ideas for your Company | D38: 44589 | E38: 6831
A39: LinkedIn | B39: PNC | C39: PNC Institutional Asset Management | D39: 44589 | E39: 6626
A40: LinkedIn | B40: PNC | C40: PNC Wealth Management | D40: 44589 | E40: NA
A41: LinkedIn | B41: SunTrust | C41: SunTrust | D41: 44589 | E41: 121,250
A42: LinkedIn | B42: SunTrust | C42: SunTrust Robinson Humphrey | D42: 44589 | E42: 12054
A43: LinkedIn | B43: SunTrust | C43: SunTrust Investment Services, Inc. | D43: 44589 | E43: 5129
A44: LinkedIn | B44: SunTrust | C44: Sun Trust Small Businesses | D44: 44589 | E44: 929
A45: LinkedIn | B45: SunTrust | C45: Sun Trust Commercial Real Estate | D45: 44589 | E45: 2958
A46: LinkedIn | B46: US Bank | C46: U.S. Bank | D46: 44589 | E46: 346569
A47: LinkedIn | B47: US Bank | C47: U.S. Bancorp Investments, Inc. | D47: 44589 | E47: 4625
A48: LinkedIn | B48: US Bank | C48: U.S. Bank Corporate payment Sytems | D48: 44589 | E48: 7471
A49: LinkedIn | B49: US Bank | C49: U.S. Bank investment Services | D49: 44589 | E49: 3345
A50: LinkedIn | B50: US Bank | C50: U.S . Bank Global Fund Services - Europe | D50: 44589 | E50: 743
A51: LinkedIn | B51: US Bank | C51: U.S. Bank Corporate and Commercial Banking | D51: 44589 | E51: 9236
A52: Twitter | B52: Bank of America | C52: Bank of America | D52: 44589 | E52: 715900
A53: Twitter | B53: Bank of America | C53: Bank of America News | D53: 44589 | E53: 467600
... A72: Twitter | B72: Wells Fargo | C72: Ask Wells Fargo | D72: 44589 | E72: 69100
A73: Twitter | B73: Wells Fargo | C73: Wells Fargo Careers | D73: 44589 | E73: NA
A74: Twitter | B74: Wells Fargo | C74: Wells Fargo Wealth & Investment Management | D74: 44589 | E74: 21900
A75: Twitter | B75: Wells Fargo | C75: Wells Fargo AssetMgt | D75: 44589 | E75: NA
A76: Twitter | B76: PNC | C76: PNC Bank | D76: 44589 | E76: 37500
A77: Twitter | B77: PNC | C77: PNC Bank Help | D77: 44589 | E77: 43500
A78: Twitter | B78: PNC | C78: PNC News | D78: 44589 | E78: 26300
A79: Twitter | B79: SunTrust | C79: SunTrust | D79: 44589 | E79: 24300
A80: Twitter | B80: SunTrust | C80: Ask SunTrust | D80: 44589 | E80: 12500
A81: Twitter | B81: US Bank | C81: US Bank | D81: 44589 | E81: 43700
A82: Twitter | B82: US Bank | C82: Ask US Bank | D82: 44589 | E82: 12700
A83: Twitter | B83: US Bank | C83: us bank payments | D83: 44589 | E83: 972
A84: Instagram | B84: Bank of America | C84: bankofamerica | D84: 44589 | E84: 18500
A85: Instagram | B85: Capital One | C85: capitalone | D85: 44589 | E85: 98500
A86: Instagram | B86: Capital One | C86: capitalonecareers | D86: 44589 | E86: 6440
A87: Instagram | B87: Capital One | C87: capitalonecafe | D87: 44589 | E87: 7685
A88: Instagram | B88: Capital One | C88: capitalonebusiness | D88: 44589 | E88: 13600
A89: Instagram | B89: Chase | C89: chase | D89: 44589 | E89: 21700 | S89: 3307
A90: Instagram | B90: Citi | C90: Citibank | D90: 44589 | E90: 77400
A91: Instagram | B91: Citi | C91: Citi | D91: 44589 | E91: 79100
A92: Instagram | B92: Wells Fargo | C92: Wellsfargo | D92: 44589 | E92: 11000
A93: Instagram | B93: PNC | C93: PNC | D93: 44589 | E93: 21800
A94: Instagram | B94: SunTrust | C94: suntrust | D94: 44589 | E94: 13100
A95: Instagram | B95: US Bank | C95: usbank | D95: 44589 | E95: 29200
A96: Facebook | B96: Bank of America | C96: Bank of America | D96: 44617 | E96: 2778738
A97: Facebook | B97: Capital One | C97: Capital One | D97: 44617 | E97: 3950941
A98: Facebook | B98: Capital One | C98: Capital One Café | D98: 44617 | E98: 96726
A99: Facebook | B99: Capital One | C99: Capital One Careers | D99: 44617 | E99: 14799
A100: Facebook | B100: Capital One | C100: CapitalOne Business | D100: 44617 | E100: 159863
A101: Facebook | B101: Chase | C101: Chase | D101: 44617 | E101: 3700796
... A127: LinkedIn | B127: Wells Fargo | C127: Wells Fargo Advisors | D127: 44617 | E127: 95545
A128: LinkedIn | B128: Wells Fargo | C128: Wells Fargo Asset Management | D128: 44617 | E128: NA
A129: LinkedIn | B129: PNC | C129: PNC | D129: 44617 | E129: 227360
A130: LinkedIn | B130: PNC | C130: PNC Business Banking | D130: 44617 | E130: 13235
A131: LinkedIn | B131: PNC | C131: PNC Investments | D131: 44617 | E131: NA
A132: LinkedIn | B132: PNC | C132: PNC Ideas for your Company | D132: 44617 | E132: 6930
A133: LinkedIn | B133: PNC | C133: PNC Institutional Asset Management | D133: 44617 | E133: 6856
A134: LinkedIn | B134: PNC | C134: PNC Wealth Management | D134: 44617 | E134: NA
A135: LinkedIn | B135: SunTrust | C135: SunTrust | D135: 44617 | E135: 121134
A136: LinkedIn | B136: SunTrust | C136: SunTrust Robinson Humphrey | D136: 44617 | E136: 12049
A137: LinkedIn | B137: SunTrust | C137: SunTrust Investment Services, Inc. | D137: 44617 | E137: 5121
A138: LinkedIn | B138: SunTrust | C138: Sun Trust Small Businesses | D138: 44617 | E138: 924
A139: LinkedIn | B139: SunTrust | C139: Sun Trust Commercial Real Estate | D139: 44617 | E139: NA
A140: LinkedIn | B140: US Bank | C140: U.S. Bank | D140: 44617 | E140: 351513
A141: LinkedIn | B141: US Bank | C141: U.S. Bancorp Investments, Inc. | D141: 44617 | E141: NA
A142: LinkedIn | B142: US Bank | C142: U.S. Bank Corporate payment Sytems | D142: 44617 | E142: NA
A143: LinkedIn | B143: US Bank | C143: U.S. Bank investment Services | D143: 44617 | E143: NA
A144: LinkedIn | B144: US Bank | C144: U.S . Bank Global Fund Services - Europe | D144: 44617 | E144: NA
A145: LinkedIn | B145: US Bank | C145: U.S. Bank Corporate and Commercial Banking | D145: 44617 | E145: NA
A146: Twitter | B146: Bank of America | C146: Bank of America | D146: 44617 | E146: 747500
A147: Twitter | B147: Bank of America | C147: Bank of America News | D147: 44617 | E147: 501500
A148: Twitter | B148: Bank of America | C148: Bank of America Help | D148: 44617 | E148: 129100
A149: Twitter | B149: Bank of America | C149: Bank of America Business Insights | D149: 44617 | E149: 135600
A150: Twitter | B150: Bank of America | C150: Bank of America Tips | D150: 44617 | E150: 158100
A151: Twitter | B151: Bank of America | C151: Bank of America Private Bank | D151: 44617 | E151: 17200
A152: Twitter | B152: Capital One | C152: Capital One | D152: 44617 | E152: 203400
A153: Twitter | B153: Capital One | C153: Ask Capital One | D153: 44617 | E153: 116100
A154: Twitter | B154: Capital One | C154: Capital One Café | D154: 44617 | E154: 47800
A155: Twitter | B155: Capital One | C155: Capital One Careers | D155: 44617 | E155: 3345
A156: Twitter | B156: Capital One | C156: Capital One Tech | D156: 44617 | E156: 6911
A157: Twitter | B157: Capital One | C157: Capital One Stories | D157: 44617 | E157: 6991
... A166: Twitter | B166: Wells Fargo | C166: Ask Wells Fargo | D166: 44617 | E166: 69200
A167: Twitter | B167: Wells Fargo | C167: Wells Fargo Careers | D167: 44617 | E167: NA
A168: Twitter | B168: Wells Fargo | C168: Wells Fargo Wealth & Investment Management | D168: 44617 | E168: 21900
A169: Twitter | B169: Wells Fargo | C169: Wells Fargo AssetMgt | D169: 44617 | E169: NA
A170: Twitter | B170: PNC | C170: PNC Bank | D170: 44617 | E170: 37700
...

Sheet Headline Pivots
B1: =A4 -> 44589 | C1: =OFFSET(A4,COUNTA(A4:A29)-2,) -> 44914 | E1: =B2&" to "&C2 -> Jan to Dec
B2: =TEXT(B1,"mmm") -> Jan | C2: =TEXT(C1,"mmm") -> Dec
A3: Row Labels | B3: Sum of Followers
A4: 44589 | B4: 30555683 | H4: Row Labels | I4: Sum of Followers | L4: Row Labels | M4: Sum of Followers
A5: 44617 | B5: 30713261 | H5: 44589 | I5: 30555683 | L5: Facebook | M5: 0.45391106
A6: 44645 | B6: 31752268 | H6: 44617 | I6: 30713261 | L6: Instagram | M6: 0.02516998
A7: 44679 | B7: 31985641 | H7: 44645 | I7: 31752268 | L7: LinkedIn | M7: 0.38219994
A8: 44708 | B8: 32878455 | H8: 44679 | I8: 31985641 | L8: Twitter | M8: 0.13871902
A9: 44739 | B9: 32426768 | H9: 44708 | I9: 32878455 | L9: Grand Total | M9: 1
A10: 44771 | B10: 32693312 | H10: 44739 | I10: 32426768
A11: 44802 | B11: 33324291 | H11: 44771 | I11: 32693312
A12: 44834 | B12: 33627178 | H12: 44802 | I12: 33324291
A13: 44862 | B13: 33896726 | H13: 44834 | I13: 33627178
A14: 44893 | B14: 34082498 | H14: 44862 | I14: 33896726
A15: 44914 | B15: 34206582 | H15: 44893 | I15: 34082498
A16: Grand Total | B16: 392142663 | H16: 44914 | I16: 34206582
H17: Grand Total | I17: 392142663

Sheet Bank Pivots
A1: Row Labels | B1: Sum of Followers
A2: Chase | B2: 106290171
A3: Bank of America | B3: 99986214
A4: Citi | B4: 95102109 | H4: Chase | I4: 50612307 | J4: =REPT("|",B2/MAX($B$2:$B$10)*100) -> |||||||||||||||||||||||||||
A5: Capital One | B5: 64886458 | H5: Bank of America | I5: 45883154 | J5: =REPT("|",B3/MAX($B$2:$B$10)*100) -> |||||||||||||||||||||||||
A6: US Bank | B6: 11760816 | H6: Citi | I6: 40470770 | J6: =REPT("|",B4/MAX($B$2:$B$10)*100) -> ||||||||||||||||||||||||
A7: PNC | B7: 9091220 | H7: Capital One | I7: 28040534 | J7: =REPT("|",B5/MAX($B$2:$B$10)*100) -> ||||||||||||||||
A8: Truist | B8: 5025675 | H8: Wells Fargo | I8: 20480961 | J8: =REPT("|",B6/MAX($B$2:$B$10)*100) -> ||
A9: Grand Total | B9: 392142663 | H9: US Bank | I9: 4076418 | J9: =REPT("|",B7/MAX($B$2:$B$10)*100) -> ||
H10: PNC | I10: 3824187 | J10: =REPT("|",B8/MAX($B$2:$B$10)*100) -> |
H11: Truist | I11: 1472881 | J11: =REPT("|",B9/MAX($B$2:$B$10)*100) -> ||||||||||||||||||||||||||||||||||||||||||||||||||||||||||||||||||||||||||||||||||||||||||||||||||||
H12: SunTrust | I12: 765619 | J12: =REPT("|",B10/MAX($B$2:$B$10)*100)
H13: SunTrust | I13: 6663 | J13: =REPT("|",B11/MAX($B$2:$B$10)*100)
H17: US | I17: 0.247
H18: India | I18: 0.105
H19: Australia | I19: 0.069
H20: UK | I20: 0.054
H21: Russia | I21: 0.049
A26: Bank | B26: (Multiple Items)
A28: Sum of Followers | B28: Column Labels
A29: Row Labels | B29: Facebook | C29: Instagram | D29: LinkedIn | E29: Twitter | F29: Grand Total
A30: 44589 | B30: 14546548 | C30: 373925 | D30: 11347989 | E30: 4287221 | F30: 30555683 | R30: Sum of Followers | S30: Column Labels
A31: 44617 | B31: 14543591 | C31: 350252 | D31: 11459292 | E31: 4360126 | F31: 30713261 | R31: Row Labels | S31: Chase | T31: Bank of America | U31: Citi | V31: Capital One | W31: US Bank | X31: PNC | Y31: Truist | Z31: Grand Total
A32: 44645 | B32: 14894072 | C32: 815663 | D32: 11600176 | E32: 4442357 | F32: 31752268 | R32: 44589 | S32: 8321413 | T32: 7719740 | U32: 7674311 | V32: 5334658 | W32: 785425 | X32: 720136 | Z32: 30555683
A33: 44679 | B33: 14888169 | C33: 838628 | D33: 11757159 | E33: 4501685 | F33: 31985641 | R33: 44617 | S33: 8425861 | T33: 7823131 | U33: 7720310 | V33: 5251813 | W33: 767368 | X33: 724778 | Z33: 30713261
A34: 44708 | B34: 14885505 | C34: 855943 | D34: 12627283 | E34: 4509724 | F34: 32878455 | R34: 44645 | S34: 8616348 | T34: 8096763 | U34: 7760629 | V34: 5353297 | W34: 786087 | X34: 739524 | Y34: 399620 | Z34: 31752268
A35: 44739 | B35: 14881830 | C35: 848355 | D35: 12182209 | E35: 4514374 | F35: 32426768 | R35: 44679 | S35: 8683649 | T35: 8190208 | U35: 7807830 | V35: 5363592 | W35: 793821 | X35: 744599 | Y35: 401942 | Z35: 31985641
A36: 44771 | B36: 14888588 | C36: 904034 | D36: 12367051 | E36: 4533639 | F36: 32693312 | R36: 44708 | S36: 8742530 | T36: 8841697 | U36: 7847917 | V36: 5371452 | W36: 815774 | X36: 748987 | Y36: 510098 | Z36: 32878455
A37: 44802 | B37: 14891551 | C37: 917313 | D37: 12915175 | E37: 4600252 | F37: 33324291 | R37: 44739 | S37: 8823285 | T37: 8272128 | U37: 7891065 | V37: 5383881 | W37: 787553 | X37: 754130 | Y37: 514726 | Z37: 32426768
A38: 44834 | B38: 14904113 | C38: 950813 | D38: 13157429 | E38: 4614823 | F38: 33627178 | R38: 44771 | S38: 8902520 | T38: 8338172 | U38: 7942908 | V38: 5397857 | W38: 831633 | X38: 760161 | Y38: 520061 | Z38: 32693312
A39: 44862 | B39: 14882289 | C39: 981275 | D39: 13343446 | E39: 4689716 | F39: 33896726 | R39: 44802 | S39: 8982082 | T39: 8223461 | U39: 7993758 | V39: 5623878 | W39: 1210947 | X39: 764953 | Y39: 525212 | Z39: 33324291
A40: 44893 | B40: 14892738 | C40: 1009854 | D40: 13507362 | E40: 4672544 | F40: 34082498 | R40: 44834 | S40: 9092227 | T40: 8515594 | U40: 8058107 | V40: 5429806 | W40: 1225978 | X40: 773359 | Y40: 532107 | Z40: 33627178
A41: 44914 | B41: 14898897 | C41: 1024168 | D41: 13612331 | E41: 4671186 | F41: 34206582 | R41: 44862 | S41: 9176550 | T41: 8623566 | U41: 8098585 | V41: 5441602 | W41: 1238805 | X41: 781157 | Y41: 536461 | Z41: 33896726
A42: Grand Total | B42: 177997891 | C42: 9870223 | D42: 149876902 | E42: 54397647 | F42: 392142663 | R42: 44893 | S42: 9240574 | T42: 8657567 | U42: 8140167 | V42: 5462796 | W42: 1253199 | X42: 787109 | Y42: 541086 | Z42: 34082498
R43: 44914 | S43: 9283132 | T43: 8684187 | U43: 8166522 | V43: 5471826 | W43: 1264226 | X43: 792327 | Y43: 544362 | Z43: 34206582
R44: Grand Total | S44: 106290171 | T44: 99986214 | U44: 95102109 | V44: 64886458 | W44: 11760816 | X44: 9091220 | Y44: 5025675 | Z44: 392142663

Sheet SparklinePivot
A1: Platform | B1: (All)
A3: Sum of Followers | B3: Column Labels
A4: Row Labels | B4: 44589 | C4: 44617 | D4: 44645 | E4: 44679 | F4: 44708 | G4: 44739 | H4: 44771 | I4: 44802 | J4: 44834 | K4: 44862 | L4: 44893 | M4: 44914 | N4: Grand Total
A5: Chase | B5: 8321413 | C5: 8425861 | D5: 8616348 | E5: 8683649 | F5: 8742530 | G5: 8823285 | H5: 8902520 | I5: 8982082 | J5: 9092227 | K5: 9176550 | L5: 9240574 | M5: 9283132 | N5: 106290171
A6: Bank of America | B6: 7719740 | C6: 7823131 | D6: 8096763 | E6: 8190208 | F6: 8841697 | G6: 8272128 | H6: 8338172 | I6: 8223461 | J6: 8515594 | K6: 8623566 | L6: 8657567 | M6: 8684187 | N6: 99986214
A7: Citi | B7: 7674311 | C7: 7720310 | D7: 7760629 | E7: 7807830 | F7: 7847917 | G7: 7891065 | H7: 7942908 | I7: 7993758 | J7: 8058107 | K7: 8098585 | L7: 8140167 | M7: 8166522 | N7: 95102109
A8: Capital One | B8: 5334658 | C8: 5251813 | D8: 5353297 | E8: 5363592 | F8: 5371452 | G8: 5383881 | H8: 5397857 | I8: 5623878 | J8: 5429806 | K8: 5441602 | L8: 5462796 | M8: 5471826 | N8: 64886458
A9: US Bank | B9: 785425 | C9: 767368 | D9: 786087 | E9: 793821 | F9: 815774 | G9: 787553 | H9: 831633 | I9: 1210947 | J9: 1225978 | K9: 1238805 | L9: 1253199 | M9: 1264226 | N9: 11760816
A10: PNC | B10: 720136 | C10: 724778 | D10: 739524 | E10: 744599 | F10: 748987 | G10: 754130 | H10: 760161 | I10: 764953 | J10: 773359 | K10: 781157 | L10: 787109 | M10: 792327 | N10: 9091220
A11: Truist | D11: 399620 | E11: 401942 | F11: 510098 | G11: 514726 | H11: 520061 | I11: 525212 | J11: 532107 | K11: 536461 | L11: 541086 | M11: 544362 | N11: 5025675
A12: Grand Total | B12: 30555683 | C12: 30713261 | D12: 31752268 | E12: 31985641 | F12: 32878455 | G12: 32426768 | H12: 32693312 | I12: 33324291 | J12: 33627178 | K12: 33896726 | L12: 34082498 | M12: 34206582 | N12: 392142663
A26: Platform | B26: (All)
A28: Sum of Followers | B28: Column Labels
A29: Row Labels | B29: 44589 | C29: 44617 | D29: 44645 | E29: 44679 | F29: 44708 | G29: 44739 | H29: 44771 | I29: 44802 | J29: 44834 | K29: 44862 | L29: 44893 | M29: 44914
A30: Chase | B30: 8321413 | C30: 8425861 | D30: 8616348 | E30: 8683649 | F30: 8742530 | G30: 8823285 | H30: 8902520 | I30: 8982082 | J30: 9092227 | K30: 9176550 | L30: 9240574 | M30: 9283132
A31: Bank of America | B31: 7719740 | C31: 7823131 | D31: 8096763 | E31: 8190208 | F31: 8841697 | G31: 8272128 | H31: 8338172 | I31: 8223461 | J31: 8515594 | K31: 8623566 | L31: 8657567 | M31: 8684187
A32: Citi | B32: 7674311 | C32: 7720310 | D32: 7760629 | E32: 7807830 | F32: 7847917 | G32: 7891065 | H32: 7942908 | I32: 7993758 | J32: 8058107 | K32: 8098585 | L32: 8140167 | M32: 8166522
A33: Capital One | B33: 5334658 | C33: 5251813 | D33: 5353297 | E33: 5363592 | F33: 5371452 | G33: 5383881 | H33: 5397857 | I33: 5623878 | J33: 5429806 | K33: 5441602 | L33: 5462796 | M33: 5471826
A34: US Bank | B34: 785425 | C34: 767368 | D34: 786087 | E34: 793821 | F34: 815774 | G34: 787553 | H34: 831633 | I34: 1210947 | J34: 1225978 | K34: 1238805 | L34: 1253199 | M34: 1264226
A35: PNC | B35: 720136 | C35: 724778 | D35: 739524 | E35: 744599 | F35: 748987 | G35: 754130 | H35: 760161 | I35: 764953 | J35: 773359 | K35: 781157 | L35: 787109 | M35: 792327
A36: Truist | D36: 399620 | E36: 401942 | F36: 510098 | G36: 514726 | H36: 520061 | I36: 525212 | J36: 532107 | K36: 536461 | L36: 541086 | M36: 544362
A37: Grand Total | B37: 30555683 | C37: 30713261 | D37: 31752268 | E37: 31985641 | F37: 32878455 | G37: 32426768 | H37: 32693312 | I37: 33324291 | J37: 33627178 | K37: 33896726 | L37: 34082498 | M37: 34206582
A47: Platform | B47: (All)
A49: Sum of Followers | B49: Column Labels
A50: Row Labels | B50: 44589 | C50: 44617 | D50: 44645 | E50: 44679 | F50: 44708 | G50: 44739 | H50: 44771 | I50: 44802 | J50: 44834 | K50: 44862 | L50: 44893 | M50: 44914
A51: Chase | B51: 8321413 | C51: 8425861 | D51: 8616348 | E51: 8683649 | F51: 8742530 | G51: 8823285 | H51: 8902520 | I51: 8982082 | J51: 9092227 | K51: 9176550 | L51: 9240574 | M51: 9283132
A52: Bank of America | B52: 7719740 | C52: 7823131 | D52: 8096763 | E52: 8190208 | F52: 8841697 | G52: 8272128 | H52: 8338172 | I52: 8223461 | J52: 8515594 | K52: 8623566 | L52: 8657567 | M52: 8684187
A53: Citi | B53: 7674311 | C53: 7720310 | D53: 7760629 | E53: 7807830 | F53: 7847917 | G53: 7891065 | H53: 7942908 | I53: 7993758 | J53: 8058107 | K53: 8098585 | L53: 8140167 | M53: 8166522
A54: Capital One | B54: 5334658 | C54: 5251813 | D54: 5353297 | E54: 5363592 | F54: 5371452 | G54: 5383881 | H54: 5397857 | I54: 5623878 | J54: 5429806 | K54: 5441602 | L54: 5462796 | M54: 5471826
A55: US Bank | B55: 785425 | C55: 767368 | D55: 786087 | E55: 793821 | F55: 815774 | G55: 787553 | H55: 831633 | I55: 1210947 | J55: 1225978 | K55: 1238805 | L55: 1253199 | M55: 1264226
A56: PNC | B56: 720136 | C56: 724778 | D56: 739524 | E56: 744599 | F56: 748987 | G56: 754130 | H56: 760161 | I56: 764953 | J56: 773359 | K56: 781157 | L56: 787109 | M56: 792327
A57: Truist | D57: 399620 | E57: 401942 | F57: 510098 | G57: 514726 | H57: 520061 | I57: 525212 | J57: 532107 | K57: 536461 | L57: 541086 | M57: 544362
A58: Grand Total | B58: 30555683 | C58: 30713261 | D58: 31752268 | E58: 31985641 | F58: 32878455 | G58: 32426768 | H58: 32693312 | I58: 33324291 | J58: 33627178 | K58: 33896726 | L58: 34082498 | M58: 34206582
A69: Platform | B69: (All)
A71: Sum of Followers | B71: Column Labels
A72: Row Labels | B72: 44589 | C72: 44617 | D72: 44645 | E72: 44679 | F72: 44708 | G72: 44739 | H72: 44771 | I72: 44802 | J72: 44834 | K72: 44862 | L72: 44893 | M72: 44914
A73: Chase | B73: 8321413 | C73: 8425861 | D73: 8616348 | E73: 8683649 | F73: 8742530 | G73: 8823285 | H73: 8902520 | I73: 8982082 | J73: 9092227 | K73: 9176550 | L73: 9240574 | M73: 9283132
A74: Bank of America | B74: 7719740 | C74: 7823131 | D74: 8096763 | E74: 8190208 | F74: 8841697 | G74: 8272128 | H74: 8338172 | I74: 8223461 | J74: 8515594 | K74: 8623566 | L74: 8657567 | M74: 8684187
A75: Citi | B75: 7674311 | C75: 7720310 | D75: 7760629 | E75: 7807830 | F75: 7847917 | G75: 7891065 | H75: 7942908 | I75: 7993758 | J75: 8058107 | K75: 8098585 | L75: 8140167 | M75: 8166522
A76: Capital One | B76: 5334658 | C76: 5251813 | D76: 5353297 | E76: 5363592 | F76: 5371452 | G76: 5383881 | H76: 5397857 | I76: 5623878 | J76: 5429806 | K76: 5441602 | L76: 5462796 | M76: 5471826
A77: US Bank | B77: 785425 | C77: 767368 | D77: 786087 | E77: 793821 | F77: 815774 | G77: 787553 | H77: 831633 | I77: 1210947 | J77: 1225978 | K77: 1238805 | L77: 1253199 | M77: 1264226
A78: PNC | B78: 720136 | C78: 724778 | D78: 739524 | E78: 744599 | F78: 748987 | G78: 754130 | H78: 760161 | I78: 764953 | J78: 773359 | K78: 781157 | L78: 787109 | M78: 792327
A79: Truist | D79: 399620 | E79: 401942 | F79: 510098 | G79: 514726 | H79: 520061 | I79: 525212 | J79: 532107 | K79: 536461 | L79: 541086 | M79: 544362
A80: Grand Total | B80: 30555683 | C80: 30713261 | D80: 31752268 | E80: 31985641 | F80: 32878455 | G80: 32426768 | H80: 32693312 | I80: 33324291 | J80: 33627178 | K80: 33896726 | L80: 34082498 | M80: 34206582
A89: Platform | B89: (All)
A91: Sum of Followers | B91: Column Labels
A92: Row Labels | B92: 44589 | C92: 44617 | D92: 44645 | E92: 44679 | F92: 44708 | G92: 44739 | H92: 44771 | I92: 44802 | J92: 44834 | K92: 44862 | L92: 44893 | M92: 44914
A93: Chase | B93: 8321413 | C93: 8425861 | D93: 8616348 | E93: 8683649 | F93: 8742530 | G93: 8823285 | H93: 8902520 | I93: 8982082 | J93: 9092227 | K93: 9176550 | L93: 9240574 | M93: 9283132
A94: Bank of America | B94: 7719740 | C94: 7823131 | D94: 8096763 | E94: 8190208 | F94: 8841697 | G94: 8272128 | H94: 8338172 | I94: 8223461 | J94: 8515594 | K94: 8623566 | L94: 8657567 | M94: 8684187
A95: Citi | B95: 7674311 | C95: 7720310 | D95: 7760629 | E95: 7807830 | F95: 7847917 | G95: 7891065 | H95: 7942908 | I95: 7993758 | J95: 8058107 | K95: 8098585 | L95: 8140167 | M95: 8166522
A96: Capital One | B96: 5334658 | C96: 5251813 | D96: 5353297 | E96: 5363592 | F96: 5371452 | G96: 5383881 | H96: 5397857 | I96: 5623878 | J96: 5429806 | K96: 5441602 | L96: 5462796 | M96: 5471826
A97: US Bank | B97: 785425 | C97: 767368 | D97: 786087 | E97: 793821 | F97: 815774 | G97: 787553 | H97: 831633 | I97: 1210947 | J97: 1225978 | K97: 1238805 | L97: 1253199 | M97: 1264226
A98: PNC | B98: 720136 | C98: 724778 | D98: 739524 | E98: 744599 | F98: 748987 | G98: 754130 | H98: 760161 | I98: 764953 | J98: 773359 | K98: 781157 | L98: 787109 | M98: 792327
A99: Truist | D99: 399620 | E99: 401942 | F99: 510098 | G99: 514726 | H99: 520061 | I99: 525212 | J99: 532107 | K99: 536461 | L99: 541086 | M99: 544362
A100: Grand Total | B100: 30555683 | C100: 30713261 | D100: 31752268 | E100: 31985641 | F100: 32878455 | G100: 32426768 | H100: 32693312 | I100: 33324291 | J100: 33627178 | K100: 33896726 | L100: 34082498 | M100: 34206582

Sheet Pivot
A3: Sum of Followers | B3: Column Labels
A4: Row Labels | B4: 44589 | C4: 44617 | D4: 44645 | E4: 44679 | F4: 44708 | G4: 44739 | H4: 44771 | I4: 44802 | J4: 44834 | K4: 44862 | L4: 44893 | M4: 44914
A5: Facebook | B5: 16007096 | C5: 16005197 | D5: 16231470 | E5: 16226366 | F5: 16224753 | G5: 16222312 | H5: 16230947 | I5: 16235200 | J5: 16251527 | K5: 16228186 | L5: 16241303 | M5: 16249524
A6: Bank of America | B6: 2779295 | C6: 2778738 | D6: 2778425 | E6: 2776304 | F6: 2774869 | G6: 2771783 | H6: 2770986 | I6: 2769931 | J6: 2769844 | K6: 2760730 | L6: 2762446 | M6: 2764492
A7: Capital One | B7: 3952818 | C7: 3950941 | D7: 3949311 | E7: 3946446 | F7: 3944152 | G7: 3942104 | H7: 3941761 | I7: 3941267 | J7: 3941402 | K7: 3934914 | L7: 3935889 | M7: 3936662
A8: Capital One Café | B8: 96736 | C8: 96726 | D8: 96763 | E8: 96710 | F8: 96663 | G8: 96543 | H8: 96650 | I8: 96789 | J8: 97107 | K8: 96939 | L8: 97144 | M8: 97239
A9: Capital One Careers | B9: 14777 | C9: 14799 | D9: 14806 | E9: 14830 | F9: 14832 | G9: 14844 | H9: 14871 | I9: 14885 | J9: 14914 | K9: 14493 | L9: 14973 | M9: 14997
A10: CapitalOne Business | B10: 160008 | C10: 159863 | D10: 159843 | E10: 159735 | F10: 159632 | G10: 159509 | H10: 159393 | I10: 159372 | J10: 159419 | K10: 159077 | L10: 159333 | M10: 159666
A11: Chase | B11: 3702495 | C11: 3700796 | D11: 3698498 | E11: 3696610 | F11: 3694950 | G11: 3694322 | H11: 3693407 | I11: 3692814 | J11: 3695549 | K11: 3693605 | L11: 3694207 | M11: 3693408
A12: Citi | B12: 1201072 | C12: 1200821 | D12: 1200549 | E12: 1200654 | F12: 1201378 | G12: 1202085 | H12: 1204171 | I12: 1205876 | J12: 1208684 | K12: 1206979 | L12: 1208969 | M12: 1209611
A13: Citi Careers | B13: 215149 | C13: 215186 | D13: 215224 | E13: 215514 | F13: 215622 | G13: 215504 | H13: 215734 | I13: 215693 | J13: 215949 | K13: 215900 | L13: 215971 | M13: 215925
A14: Citibank US | B14: 1144626 | C14: 1144064 | D14: 1143581 | E14: 1142593 | F14: 1142056 | G14: 1141647 | H14: 1142016 | I14: 1142147 | J14: 1142529 | K14: 1139664 | L14: 1140596 | M14: 1140883
A15: JPMorgan Chase & Co. | B15: 400833 | C15: 402700 | D15: 404063 | E15: 405302 | F15: 407314 | G15: 408930 | H15: 412974 | I15: 414907 | J15: 417581 | K15: 419210 | L15: 420732 | M15: 421845
A16: PNC | B16: 339417 | C16: 339697 | D16: 340066 | E16: 340609 | F16: 341153 | G16: 341591 | H16: 342672 | I16: 343275 | J16: 344400 | K16: 344587 | L16: 345271 | M16: 345942
A17: SunTrust | B17: 125124 | C17: 125124
A18: Truist | D18: 353505 | E18: 353442 | F18: 353390 | G18: 353189 | H18: 353329 | I18: 353601 | J18: 354647 | K18: 354406 | L18: 354743 | M18: 354976
A19: U.S. Bank | B19: 326864 | C19: 326976 | D19: 327253 | E19: 327376 | F19: 327612 | G19: 328074 | H19: 328999 | I19: 329481 | J19: 330705 | K19: 330632 | L19: 331464 | M19: 332344
A20: United MileagePlus Cards by Chase | B20: 212458 | C20: 212284 | D20: 212185 | E20: 212044 | F20: 211882 | G20: 211705 | H20: 211625 | I20: 211513 | J20: 211383 | K20: 211153 | L20: 211000 | M20: 210907
A21: Wells Fargo | B21: 1141858 | C21: 1143100 | D21: 1144120 | E21: 1145101 | F21: 1146324 | G21: 1147764 | H21: 1150804 | I21: 1152196 | J21: 1156046 | K21: 1155099 | L21: 1157926 | M21: 1160083
A22: Wells Fargo Advisor | B22: 192513 | C22: 192329 | D22: 192214 | E22: 192027 | F22: 191854 | G22: 191643 | H22: 191555 | I22: 191453 | J22: 191368 | K22: 190798 | L22: 190639 | M22: 190544
A23: Wells Fargo Home Mortgage | B23: 1053 | C23: 1053 | D23: 1064 | E23: 1069 | F23: 1070 | G23: 1075 | H23: 0 | K23: 0
A24: Instagram | B24: 398025 | C24: 475852 | D24: 928663 | E24: 952628 | F24: 969943 | G24: 965355 | H24: 1022955 | I24: 1037479 | J24: 1071511 | K24: 1103194 | L24: 1133077 | M24: 1148217
A25: bankofamerica | B25: 18500 | C25: 19000 | D25: 195000 | E25: 199000 | F25: 203000 | G25: 210000 | H25: 216431 | I25: 1005 | J25: 226873 | K25: 233176 | L25: 238739 | M25: 242077
A26: capitalone | B26: 98500 | C26: 10100 | D26: 106000 | E26: 110000 | F26: 113000 | G26: 116000 | H26: 118342 | I26: 221249 | J26: 122938 | K26: 126415 | L26: 133289 | M26: 135845
A27: capitalonebusiness | B27: 13600 | C27: 14700 | D27: 16000 | E27: 18600 | F27: 19900 | G27: 22700 | H27: 24078 | I27: 25324 | J27: 26668 | K27: 30120 | L27: 30684 | M27: 30329
A28: capitalonecafe | B28: 7685 | C28: 7784 | D28: 7926 | E28: 8048 | F28: 8139 | G28: 8263 | H28: 8958 | I28: 9367 | J28: 9781 | K28: 11711 | L28: 12441 | M28: 12819
A29: capitalonecareers | B29: 6440 | C29: 6768 | D29: 7237 | E29: 7580 | F29: 7704 | G29: 7892 | H29: 8104 | I29: 120184 | J29: 9046 | K29: 9821 | L29: 10562 | M29: 11486
A30: Chase | B30: 21700 | C30: 77700 | D30: 226000 | E30: 232000 | F30: 235000 | G30: 241000 | H30: 243009 | I30: 245180 | J30: 246657 | K30: 249721 | L30: 252454 | M30: 254795
A31: Citi | B31: 79100 | C31: 82700 | D31: 86700 | E31: 89500 | F31: 92800 | G31: 96100 | H31: 98723 | I31: 102277 | J31: 105421 | K31: 108438 | L31: 112128 | M31: 114859
A32: Citibank | B32: 77400 | C32: 77400 | D32: 78100 | E32: 78600 | F32: 79500 | G32: 81800 | H32: 84554 | I32: 89295 | J32: 96804 | K32: 101512 | L32: 105851 | M32: 105592
A33: PNC | B33: 21800 | C33: 22800 | D33: 23500 | E33: 24200 | F33: 24500 | G33: 25500 | H33: 25657 | I33: 25937 | J33: 26938 | K33: 28106 | L33: 29022 | M33: 29708
A34: SunTrust | B34: 13100 | C34: 13600
A35: Truist | D35: 36400 | E35: 37300 | F35: 38000 | G35: 39100 | H35: 39650 | I35: 40226 | J35: 40939 | K35: 41750 | L35: 42734 | M35: 43515
A36: usbank | B36: 29200 | C36: 31300 | D36: 32800 | E36: 33800 | F36: 34400 | H36: 36528 | I36: 37269 | J36: 38748 | K36: 40505 | L36: 41950 | M36: 43143
A37: Wellsfargo | B37: 11000 | C37: 112000 | D37: 113000 | E37: 114000 | F37: 114000 | G37: 117000 | H37: 118921 | I37: 120166 | J37: 120698 | K37: 121919 | L37: 123223 | M37: 124049
A38: LinkedIn | B38: 13198100 | C38: 13453203 | D38: 13617014 | E38: 13806837 | F38: 14562835 | G38: 14148472 | H38: 14368667 | I38: 14948267 | J38: 15233812 | K38: 15453181 | L38: 15647582 | M38: 15774044
A39: Bank of America | B39: 2028349 | C39: 2058767 | D39: 2085093 | E39: 2115895 | F39: 2774869 | G39: 2174339 | H39: 2208988 | I39: 2241791 | J39: 2285112 | K39: 2317880 | L39: 2346689 | M39: 2363476
A40: Bank of America Business | B40: 290536 | C40: 291985 | D40: 293598 | E40: 295446 | F40: 297107 | G40: 298756 | H40: 300722 | I40: 302435 | J40: 305074 | K40: 307216 | L40: 309907 | M40: 311810
A41: Bank of America Merrill Lynch | B41: 336752 | C41: 338145 | D41: 339351 | E41: 341086 | F41: 323163 | G41: 344448 | H41: 346346 | I41: 347786 | J41: 349804 | K41: 351596 | L41: 353163 | M41: 354144
A42: Capital One | B42: 532002 | C42: 536978 | D42: 541098 | E42: 546779 | F42: 551759 | G42: 559045 | H42: 566948 | I42: 575524 | J42: 587006 | K42: 594832 | L42: 601169 | M42: 605430
A43: Capital One Business | B43: 28843 | C43: 29107 | D43: 29348 | E43: 29662 | F43: 29933 | G43: 30195 | H43: 30633 | I43: 31093 | J43: 31434 | K43: 31719 | L43: 32013 | M43: 32177
A44: Chase | B44: 336631 | C44: 340831 | D44: 344321 | E44: 349611 | F44: 353706 | G44: 358090 | H44: 363155 | I44: 367441 | J44: 372926 | K44: 377396 | L44: 381531 | M44: 383931
A45: Chase for Business | B45: 36843 | C45: 36886 | D45: 36959 | E45: 37115 | F45: 37284 | G45: 37522 | H45: 37782 | I45: 38041 | J45: 38447 | K45: 38754 | L45: 39061 | M45: 39296
A46: Citi | B46: 3540466 | C46: 3578795 | D46: 3610229 | E46: 3650256 | F46: 3681638 | G46: 3715832 | H46: 3755976 | I46: 3792508 | J46: 3840034 | K46: 3873456 | L46: 3905209 | M46: 3927087
A47: Citi Private Bank | B47: 44257 | C47: 45995 | D47: 48097 | E47: 49844 | F47: 51511 | G47: 53317 | H47: 55387 | I47: 57631 | J47: 59614 | K47: 61422 | L47: 63026 | M47: 63976
A48: Citigold | B48: 12941 | C48: 13149 | D48: 13149 | E48: 13469 | F48: 13612 | G48: 13780 | H48: 13901 | I48: 14000 | J48: 14145 | K48: 14265 | L48: 14384 | M48: 14462
... A56: PNC Investments | B56: 0 | C56: 0 | D56: 10745 | E56: 10896 | F56: 11008 | G56: 11142 | H56: 11312 | I56: 11457 | J56: 11635 | K56: 11814 | L56: 11982 | M56: 12099
A57: PNC Wealth Management | B57: 0 | C57: 0 | D57: 0 | E57: 0 | F57: 0 | G57: 0 | H57: 0 | K57: 0
A58: Sun Trust Commercial Real Estate | B58: 2958 | C58: 0 | D58: 0 | E58: 0
A59: Sun Trust Small Business | E59: 929
A60: Sun Trust Small Businesses | B60: 929 | C60: 924 | D60: 923
A61: SunTrust | B61: 0 | C61: 121134 | D61: 121155 | E61: 121263
A62: SunTrust Investment Services, Inc. | B62: 5129 | C62: 5121 | D62: 5121 | E62: 5115
A63: SunTrust Robinson Humphrey | B63: 12054 | C63: 12049 | D63: 12052 | E63: 12051
A64: Truist | F64: 75749 | G64: 78329 | H64: 81435 | I64: 84175 | J64: 87644 | K64: 90184 | L64: 92433 | M64: 93878
A65: Truist Commercial, Corporate & Institutional | F65: 8399 | G65: 8565 | H65: 8858 | I65: 9046 | J65: 9248 | K65: 9386 | L65: 9475 | M65: 9584
A66: Truist Insurance Holdings,Inc | F66: 9725 | G66: 9850 | H66: 10046 | I66: 10250 | J66: 10427 | K66: 10557 | L66: 10677 | M66: 10787
A67: Truist Securities | F67: 5600 | G67: 5840 | H67: 6112 | I67: 6431 | J67: 6986 | K67: 7513 | L67: 8125 | M67: 8391
A68: Truist Wealth | F68: 7635 | G68: 7853 | H68: 8205 | I68: 8545 | J68: 8942 | K68: 9191 | L68: 9493 | M68: 9682
A69: U.S . Bank Global Fund Services - Europe | B69: 743 | C69: 0 | D69: 0 | E69: 0 | F69: 871 | G69: 894 | H69: 913 | I69: 926 | J69: 945 | K69: 961 | L69: 987 | M69: 996
A70: U.S. Bancorp Investments, Inc. | B70: 4625 | C70: 0 | D70: 4838 | E70: 4970 | F70: 5065 | G70: 5178 | H70: 5279 | I70: 5381 | J70: 5522 | K70: 5619 | L70: 5750 | M70: 5832
A71: U.S. Bank | B71: 346569 | C71: 351513 | D71: 355664 | E71: 361786 | F71: 366572 | G71: 371278 | H71: 376412 | I71: 381010 | J71: 386709 | K71: 391902 | L71: 397841 | M71: 402080
A72: U.S. Bank Corporate and Commercial Banking | B72: 9236 | C72: 0 | D72: 0 | E72: 0 | F72: 10995 | G72: 11364 | H72: 11921 | I72: 12335 | J72: 12810 | K72: 13225 | L72: 13613 | M72: 13890
A73: U.S. Bank Corporate payment Sytems | B73: 7471 | C73: 0 | D73: 7755 | E73: 7906 | F73: 8050 | G73: 8198 | H73: 8388 | I73: 381010 | J73: 386709 | K73: 391902 | L73: 397841 | M73: 402080
A74: U.S. Bank investment Services | B74: 3345 | C74: 0 | D74: 0 | E74: 0 | F74: 4023 | G74: 4179 | H74: 4379 | I74: 4517 | J74: 4681 | K74: 4864 | L74: 5081 | M74: 5204
A75: Wells Fargo | B75: 1734700 | C75: 1759138 | D75: 1780718 | E75: 1811086 | F75: 1834606 | G75: 1863267 | H75: 1896628 | I75: 1926731 | J75: 1968203 | K75: 1999645 | L75: 2028070 | M75: 2047987
A76: Wells Fargo Advisors | B76: 94341 | C76: 95545 | D76: 96869 | E76: 99234 | F76: 100946 | G76: 102996 | H76: 104988 | I76: 106361 | J76: 108180 | K76: 110090 | L76: 112150 | M76: 113726
A77: Wells Fargo Asset Management | B77: 0 | C77: 0 | D77: 0 | E77: 0 | F77: 0 | G77: 0 | H77: 0 | K77: 0
A78: Twitter | B78: 4747521 | C78: 4823426 | D78: 4870457 | E78: 4931285 | F78: 4940224 | G78: 4945374 | H78: 4967059 | I78: 5035451 | J78: 5050923 | K78: 5127573 | L78: 5108637 | M78: 5107219
A79: us bank payments | B79: 972 | C79: 979 | D79: 977 | E79: 983 | F79: 986 | G79: 988 | H79: 998 | I79: 1001 | J79: 1004 | K79: 1006 | L79: 989 | M79: 988
A80: Ask Capital One | B80: 115900 | C80: 116100 | D80: 116400 | E80: 116400 | F80: 116600 | G80: 117000 | H80: 117511 | I80: 117742 | J80: 117960 | K80: 118097 | L80: 117328 | M80: 117115
A81: Ask Citi | B81: 38000 | C81: 38000 | D81: 38300 | E81: 38400 | F81: 38600 | G81: 38700 | H81: 39021 | I81: 39297 | J81: 39490 | K81: 39578 | L81: 39348 | M81: 39380
A82: Ask SunTrust | B82: 12500 | C82: 12500
A83: Ask US Bank | B83: 12700 | C83: 12700 | D83: 12700 | E83: 12800 | F83: 12800 | G83: 12900 | H83: 12995 | I83: 13040 | J83: 13070 | K83: 13083 | L83: 12969 | M83: 12993
A84: Ask Wells Fargo | B84: 69100 | C84: 69200 | D84: 69300 | E84: 69400 | F84: 69400 | G84: 69400 | H84: 69718 | I84: 69811 | J84: 69828 | K84: 70012 | L84: 69505 | M84: 69443
A85: Bank of America | B85: 715900 | C85: 747500 | D85: 779400 | E85: 802700 | F85: 804800 | G85: 805100 | H85: 817603 | I85: 876956 | J85: 887160 | K85: 954255 | L85: 947958 | M85: 946352
A86: Bank of America Business Insights | B86: 135200 | C86: 135600 | D86: 135800 | E86: 135900 | F86: 136100 | G86: 136300 | H86: 136520 | I86: 136769 | J86: 137005 | K86: 137262 | L86: 137346 | M86: 138005
A87: Bank of America Help | B87: 128200 | C87: 129100 | D87: 130000 | E87: 130600 | F87: 131000 | G87: 131300 | H87: 131824 | I87: 132492 | J87: 133001 | K87: 133569 | L87: 132837 | M87: 132979
A88: Bank of America News | B88: 467600 | C88: 501500 | D88: 534600 | E88: 564600 | F88: 564700 | G88: 564000 | H88: 563770 | I88: 564801 | J88: 564619 | K88: 565953 | L88: 563380 | M88: 563096
A89: Bank of America Private Bank | B89: 17100 | C89: 17200 | D89: 17400 | E89: 17500 | F89: 17500 | G89: 17600 | H89: 17718 | I89: 17846 | J89: 17924 | K89: 17997 | L89: 17934 | M89: 17955
A90: Bank of America Tips | B90: 158300 | C90: 158100 | D90: 158000 | E90: 157700 | F90: 157500 | G90: 157300 | H90: 157249 | I90: 157122 | J90: 156838 | K90: 156664 | L90: 155585 | M90: 155328
A91: Capital One | B91: 202700 | C91: 203400 | D91: 204000 | E91: 204400 | F91: 204800 | G91: 205500 | H91: 206162 | I91: 206636 | J91: 207777 | K91: 209144 | L91: 214638 | M91: 214923
A92: Capital One Café | B92: 47900 | C92: 47800 | D92: 47800 | E92: 47700 | F92: 47600 | G92: 47600 | H92: 47663 | I92: 47685 | J92: 47597 | K92: 47569 | L92: 47029 | M92: 46925
A93: Capital One Careers | B93: 3342 | C93: 3345 | D93: 3353 | E93: 3362 | F93: 3367 | G93: 3379 | H93: 3407 | I93: 3413 | J93: 3421 | K93: 3429 | L93: 3382 | M93: 3377
A94: Capital One Stories | B94: 6995 | C94: 6991 | D94: 6997 | E94: 6982 | F94: 6962 | G94: 6961 | H94: 6958 | I94: 6955 | J94: 6948 | K94: 6953 | L94: 6879 | M94: 6862
... A104: PNC News | B104: 26300 | C104: 26300 | D104: 26400 | E104: 26400 | F104: 26400 | G104: 26500 | H104: 26517 | I104: 26526 | J104: 26535 | K104: 26543 | L104: 26284 | M104: 26257
A105: SunTrust | B105: 24300 | C105: 24300
A106: Truist | D106: 9715
A107: TruistNews | E107: 11200 | F107: 11600 | G107: 12000 | H107: 12426 | I107: 12938 | J107: 13274 | K107: 13474 | L107: 13406 | M107: 13549
A108: US Bank | B108: 43700 | C108: 43900 | D108: 44100 | E108: 44200 | F108: 44400 | G108: 44500 | H108: 44821 | I108: 44977 | J108: 45075 | K108: 45106 | L108: 44714 | M108: 44676
A109: Wells Fargo | B109: 332500 | C109: 335400 | D109: 336900 | E109: 338400 | F109: 339300 | G109: 339800 | H109: 341805 | I109: 343367 | J109: 344245 | K109: 345838 | L109: 344754 | M109: 344787
A110: Wells Fargo AssetMgt | B110: 0 | C110: 0 | D110: 0 | E110: 0 | F110: 0 | G110: 0 | H110: 0 | K110: 0
A111: Wells Fargo Careers | B111: 0 | C111: 0 | D111: 0 | E111: 0 | F111: 0 | G111: 0 | H111: 0 | K111: 0
A112: Wells Fargo Wealth & Investment Management | B112: 21900 | C112: 21900 | D112: 21900 | E112: 21800 | F112: 21800 | G112: 21800 | H112: 21897 | I112: 22021 | J112: 22027 | K112: 22007 | L112: 21834 | M112: 21803
